downvids/__init__.py
downvids/downvids.py
downvids-1.0.0.dist-info/LICENSE
downvids-1.0.0.dist-info/METADATA
downvids-1.0.0.dist-info/WHEEL
downvids-1.0.0.dist-info/entry_points.txt
downvids-1.0.0.dist-info/top_level.txt
downvids-1.0.0.dist-info/RECORD
